pricedb/__init__.py
pricedb/app.py
pricedb/cli.py
pricedb/config.py
pricedb/config2.py
pricedb/config_cli.py
pricedb/csv.py
pricedb/dal.py
pricedb/ledger.py
pricedb/mappers.py
pricedb/model.py
pricedb/repositories.py
pricedb/utils.py
pricedb/templates/pricedb.ini
pricedb/templates/prices-template.db
PriceDb-2.11.0.dist-info/LICENSE.txt
PriceDb-2.11.0.dist-info/METADATA
PriceDb-2.11.0.dist-info/WHEEL
PriceDb-2.11.0.dist-info/entry_points.txt
PriceDb-2.11.0.dist-info/top_level.txt
PriceDb-2.11.0.dist-info/RECORD
