Metadata-Version: 2.1
Name: PriceDb
Version: 2.11.0
Summary: Price database storage for commodities
Home-page: https://github.com/MisterY/price-database
Author: Alen Siljak
Author-email: alen@alensiljak.eu.org
License: GPL version 3
Keywords: personal finance
Platform: UNKNOWN
Classifier: Development Status :: 5 - Production/Stable
Classifier: Intended Audience :: Developers
Classifier: License :: OSI Approved :: GNU General Public License v3 (GPLv3)
Classifier: Programming Language :: Python :: 3
Classifier: Programming Language :: Python :: 3.7
Requires-Python: >=3.6
License-File: LICENSE.txt
Requires-Dist: click
Requires-Dist: click-log
Requires-Dist: sqlalchemy
Requires-Dist: beautifulsoup4
Requires-Dist: pydatum
Requires-Dist: finance-quote-python
Requires-Dist: usersconfig
